CHANGELOG
MANIFEST.in
README
setup.py
devartis_admin/__init__.py
devartis_admin/static/admin/css/devartis.css
devartis_admin/static/admin/img/logo.png
devartis_admin/templates/admin/base_site.html
devartis_admin/templatetags/__init__.py
devartis_admin/templatetags/devartis_admin.py
django_devartis_admin.egg-info/PKG-INFO
django_devartis_admin.egg-info/SOURCES.txt
django_devartis_admin.egg-info/dependency_links.txt
django_devartis_admin.egg-info/not-zip-safe
django_devartis_admin.egg-info/top_level.txt