Metadata-Version: 1.1
Name: django-devartis-admin
Version: 0.1.6
Summary: A devartis theme for the django admin site
Home-page: https://github.com/devartis/django-devartis-admin
Author: Fernando Aramendi
Author-email: fernando@devartis.com
License: MIT License
Download-URL: https://github.com/devartis/django-devartis-admin/archive/0.1.6.tar.gz
Platform: UNKNOWN
Classifier: Development Status :: 4 - Beta
Classifier: Environment :: Web Environment
Classifier: Framework :: Django
Classifier: Intended Audience :: Developers
Classifier: License :: OSI Approved :: MIT License
Classifier: Operating System :: OS Independent
Classifier: Programming Language :: Python
Classifier: Topic :: Software Development :: Libraries :: Python Modules
